MANIFEST.in
README.rst
setup.cfg
setup.py
docs/HISTORY.txt
docs/INSTALL.txt
docs/LICENSE.GPL
docs/LICENSE.txt
rt/__init__.py
rt.bulkmodify.egg-info/PKG-INFO
rt.bulkmodify.egg-info/SOURCES.txt
rt.bulkmodify.egg-info/dependency_links.txt
rt.bulkmodify.egg-info/entry_points.txt
rt.bulkmodify.egg-info/namespace_packages.txt
rt.bulkmodify.egg-info/not-zip-safe
rt.bulkmodify.egg-info/requires.txt
rt.bulkmodify.egg-info/top_level.txt
rt/bulkmodify/__init__.py
rt/bulkmodify/configure.zcml
rt/bulkmodify/interfaces.py
rt/bulkmodify/setuphandlers.py
rt/bulkmodify/testing.py
rt/bulkmodify/utility.py
rt/bulkmodify/Extensions/install.py
rt/bulkmodify/adapter/__init__.py
rt/bulkmodify/adapter/at.py
rt/bulkmodify/adapter/configure.zcml
rt/bulkmodify/browser/__init__.py
rt/bulkmodify/browser/bulk-modify.pt
rt/bulkmodify/browser/configure.zcml
rt/bulkmodify/browser/view.py
rt/bulkmodify/browser/resources/ajax-load.gif
rt/bulkmodify/browser/resources/ajax-loader-mini.gif
rt/bulkmodify/browser/resources/all.gif
rt/bulkmodify/browser/resources/bulk-modify.css
rt/bulkmodify/browser/resources/bulk-modify.js
rt/bulkmodify/handler/__init__.py
rt/bulkmodify/handler/configure.zcml
rt/bulkmodify/handler/to_uid.py
rt/bulkmodify/locales/rebuildPo.sh
rt/bulkmodify/locales/rt.bulkmodify-manual.pot
rt/bulkmodify/locales/rt.bulkmodify.pot
rt/bulkmodify/locales/it/LC_MESSAGES/rt.bulkmodify.mo
rt/bulkmodify/locales/it/LC_MESSAGES/rt.bulkmodify.po
rt/bulkmodify/profiles/default/browserlayer.xml
rt/bulkmodify/profiles/default/controlpanel.xml
rt/bulkmodify/profiles/default/cssregistry.xml
rt/bulkmodify/profiles/default/jsregistry.xml
rt/bulkmodify/profiles/default/metadata.xml
rt/bulkmodify/profiles/default/rolemap.xml
rt/bulkmodify/profiles/default/rt.bulkmodify_various.txt
rt/bulkmodify/profiles/uninstall/browserlayer.xml
rt/bulkmodify/profiles/uninstall/controlpanel.xml
rt/bulkmodify/profiles/uninstall/cssregistry.xml
rt/bulkmodify/profiles/uninstall/jsregistry.xml
rt/bulkmodify/tests/__init__.py
rt/bulkmodify/tests/base.py
rt/bulkmodify/tests/test_handler_to_uid.py
rt/bulkmodify/tests/test_template.py
rt/bulkmodify/tests/test_utility.py
rt/bulkmodify/tests/test_view.py