Metadata-Version: 1.0
Name: rt.bulkmodify
Version: 0.4.1
Summary: An administration tool for performing mass text substitution on Plone contents
Home-page: http://plone.org/products/rt.bulkmodify
Author: RedTurtle Technology
Author-email: sviluppoplone@redturtle.it
License: GPL
Keywords: plone batch bulk regex
Platform: UNKNOWN
Classifier: Development Status :: 4 - Beta
Classifier: Framework :: Plone
Classifier: Framework :: Plone :: 4.2
Classifier: Framework :: Plone :: 4.3
Classifier: Programming Language :: Python
Classifier: Programming Language :: Python :: 2.7
Classifier: Programming Language :: JavaScript
